mcp_server_dpipblock/7_dpfhq.js
mcp_server_dpipblock/__init__.py
mcp_server_dpipblock/__main__.py
mcp_server_dpipblock/common.onnx
mcp_server_dpipblock/common_det.onnx
mcp_server_dpipblock/common_old.onnx
mcp_server_dpipblock/server.py
mcp_server_dpipblock-1.0.0.dist-info/METADATA
mcp_server_dpipblock-1.0.0.dist-info/WHEEL
mcp_server_dpipblock-1.0.0.dist-info/entry_points.txt
mcp_server_dpipblock-1.0.0.dist-info/RECORD
